ccx2paraview/__init__.py
ccx2paraview/__main__.py
ccx2paraview/cli.py
ccx2paraview/common.py
ccx2paraview-3.2.0.dist-info/LICENSE
ccx2paraview-3.2.0.dist-info/METADATA
ccx2paraview-3.2.0.dist-info/WHEEL
ccx2paraview-3.2.0.dist-info/entry_points.txt
ccx2paraview-3.2.0.dist-info/top_level.txt
ccx2paraview-3.2.0.dist-info/RECORD
