Metadata-Version: 2.1
Name: ccx2paraview
Version: 3.2.0
Summary: CalculiX to Paraview converter (frd to vtk/vtu). Makes it possible to view and postprocess CalculiX analysis results in Paraview. Generates Mises and Principal components for stress and strain tensors.
Author-email: Ihor Mirzov <imirzov@gmail.com>
Maintainer-email: Ihor Mirzov <imirzov@gmail.com>
License: GPL-3.0
Project-URL: Homepage, https://github.com/calculix/ccx2paraview
Project-URL: Documentation, https://github.com/calculix/ccx2paraview
Project-URL: Repository, https://github.com/calculix/ccx2paraview
Project-URL: Bug Tracker, https://github.com/calculix/ccx2paraview/issues
Keywords: converter,vtk,vtu,paraview,calculix,frd
Classifier: Development Status :: 4 - Beta
Classifier: License :: OSI Approved :: GNU General Public License v3 (GPLv3)
Classifier: Programming Language :: Python :: 3 :: Only
Classifier: Programming Language :: Python :: 3.9
Classifier: Topic :: Scientific/Engineering
Requires-Python: >=3.9
License-File: LICENSE
Requires-Dist: numpy
Provides-Extra: vtk
Requires-Dist: vtk; extra == "vtk"
